odoo/addons/web_chatter_position/README.rst
odoo/addons/web_chatter_position/__init__.py
odoo/addons/web_chatter_position/__manifest__.py
odoo/addons/web_chatter_position/i18n/web_chatter_position.pot
odoo/addons/web_chatter_position/models/__init__.py
odoo/addons/web_chatter_position/models/res_users.py
odoo/addons/web_chatter_position/readme/CONTRIBUTORS.rst
odoo/addons/web_chatter_position/readme/DESCRIPTION.rst
odoo/addons/web_chatter_position/readme/ROADMAP.rst
odoo/addons/web_chatter_position/readme/USAGE.rst
odoo/addons/web_chatter_position/static/description/icon.png
odoo/addons/web_chatter_position/static/description/index.html
odoo/addons/web_chatter_position/static/src/js/form_chatter_position.js
odoo/addons/web_chatter_position/static/src/scss/attachment_viewer.scss
odoo/addons/web_chatter_position/static/src/scss/chatter_position.scss
odoo/addons/web_chatter_position/static/src/xml/form_buttons.xml
odoo/addons/web_chatter_position/views/assets.xml
odoo/addons/web_chatter_position/views/res_users.xml
odoo/addons/web_chatter_position/views/web.xml
odoo13_addon_web_chatter_position-13.0.1.0.1.dev3.dist-info/METADATA
odoo13_addon_web_chatter_position-13.0.1.0.1.dev3.dist-info/WHEEL
odoo13_addon_web_chatter_position-13.0.1.0.1.dev3.dist-info/top_level.txt
odoo13_addon_web_chatter_position-13.0.1.0.1.dev3.dist-info/RECORD
