Metadata-Version: 2.1
Name: odoo13-addon-web-chatter-position
Version: 13.0.1.0.1.dev3
Summary: Add an option to change the chatter position
Home-page: https://github.com/OCA/web
Author: Hynsys Technologies, Camptocamp, Odoo Community Association (OCA)
Author-email: support@odoo-community.org
License: LGPL-3
Platform: UNKNOWN
Classifier: Programming Language :: Python
Classifier: Framework :: Odoo
Classifier: Framework :: Odoo :: 13.0
Classifier: License :: OSI Approved :: GNU Lesser General Public License v3 (LGPLv3)
Requires-Python: >=3.5
Requires-Dist: odoo <13.1dev,>=13.0a
